Metadata-Version: 2.1
Name: discord-protos
Version: 0.0.2
Summary: Discord user settings protobufs.
Home-page: https://github.com/dolfies/discord-protos
Author: Dolfies
License: MIT
Project-URL: Issue tracker, https://github.com/dolfies/discord-protos/issues
Classifier: License :: OSI Approved :: MIT License
Classifier: Natural Language :: English
Classifier: Operating System :: OS Independent
Classifier: Programming Language :: Python :: 3.8
Classifier: Programming Language :: Python :: 3.9
Classifier: Programming Language :: Python :: 3.10
Classifier: Programming Language :: Python :: 3.11
Classifier: Topic :: Internet
Classifier: Topic :: Software Development :: Libraries
Classifier: Topic :: Software Development :: Libraries :: Python Modules
Classifier: Topic :: Utilities
Requires-Python: >=3.8.0
License-File: LICENSE
